setup.cfg
setup.py
mondrian_art/__init__.py
mondrian_art/mondrian_art.py
mondrian_art.egg-info/PKG-INFO
mondrian_art.egg-info/SOURCES.txt
mondrian_art.egg-info/dependency_links.txt
mondrian_art.egg-info/requires.txt
mondrian_art.egg-info/top_level.txt