Metadata-Version: 1.0
Name: mondrian-art
Version: 0.1
Summary: Generate modern art using mondrian processes.
Home-page: UNKNOWN
Author: Manoj Kumar
Author-email: UNKNOWN
License: BSD
Platform: UNKNOWN
